fastapi_logging/__init__.py
fastapi_logging/logging.py
fastapi_logging-0.1.1.dist-info/LICENSE
fastapi_logging-0.1.1.dist-info/METADATA
fastapi_logging-0.1.1.dist-info/WHEEL
fastapi_logging-0.1.1.dist-info/top_level.txt
fastapi_logging-0.1.1.dist-info/RECORD
